milvus_server/__init__.py
python_milvus_server-2.2.3.post6.dist-info/LICENSE
python_milvus_server-2.2.3.post6.dist-info/METADATA
python_milvus_server-2.2.3.post6.dist-info/WHEEL
python_milvus_server-2.2.3.post6.dist-info/top_level.txt
python_milvus_server-2.2.3.post6.dist-info/RECORD
