Metadata-Version: 2.1
Name: python-milvus-server
Version: 2.2.3.post6
Summary: Python Milvus Server
Home-page: https://github.com/matrixji/python-milvus-server
Author: Ji Bin
Author-email: matrixji@live.com
License: Apache-2.0
License-File: LICENSE
Requires-Dist: milvus (>=2.2.4)
